compspec_containment/__init__.py
compspec_containment/defaults.py
compspec_containment/plugin.py
compspec_containment/version.py
compspec_containment-0.0.14.dist-info/LICENSE
compspec_containment-0.0.14.dist-info/METADATA
compspec_containment-0.0.14.dist-info/NOTICE
compspec_containment-0.0.14.dist-info/WHEEL
compspec_containment-0.0.14.dist-info/top_level.txt
compspec_containment-0.0.14.dist-info/RECORD
